<?xml version="1.0" encoding="UTF-8"?>
<?xml-model href="../../../TAN-2018/schemas/TAN-A-lm.rnc" type="application/relax-ng-compact-syntax"?>
<?xml-model href="../../../TAN-2018/schemas/TAN-A-lm.sch" type="application/xml" schematypens="http://purl.oclc.org/dsdl/schematron"?>
<TAN-A-lm xmlns="tag:textalign.net,2015:ns"
          TAN-version="2018"
          id="tag:kalvesmaki.com,2015:tan-a-lm:lat:perseuscircul">
   <head>
      <name>Perseus lexico-morphological permutations devoted exclusively to circul</name>
      <master-location href="https://raw.githubusercontent.com/Arithmeticus/TAN-lexico-morphology/master/lat/lm-lm-perseus-2018-03-24/lat-tan-a-lm-circul.xml"/>
      <license which="Attribution-ShareAlike 3.0 Unported"/>
      <licensor who="perseus"/>
      <key>
         <IRI>tag:kalvesmaki.com,2014:tan-key:lm</IRI>
         <name>General keywords associated with Kalvesmaki's collection of lexico-morphology files</name>
         <location href="../../lm.TAN-key.xml" when-accessed="2018-03-24"/>
      </key>
      <definitions>
         <lexicon xml:id="LS" which="Lewis and Short"/>
         <morphology xml:id="perseus-dik" which="Perseus Latin morphology"/>
         <organization xml:id="perseus" which="Perseus Project"/>
         <person xml:id="dik" which="Helma Dik"/>
         <person xml:id="kalvesmaki" which="Joel Kalvesmaki"/>
         <role which="creator" xml:id="creator"/>
         <role which="sponsor" xml:id="sponsor"/>
         <role which="editor" xml:id="editor"/>
      </definitions>
      <resp who="perseus dik" roles="creator"/>
      <resp who="perseus" roles="sponsor"/>
      <resp who="kalvesmaki" roles="editor"/>
      <change when="2018-01-11" who="kalvesmaki">Started template file.</change>
      <change who="kalvesmaki" when="2018-03-24">Cleaned file for publication.</change>
   </head>
   <body lexicon="LS" morphology="perseus-dik">
      <for-lang>lat</for-lang>
      <tok-starts-with>CIrcul</tok-starts-with>
      <tok-starts-with>Circul</tok-starts-with>
      <tok-starts-with>circul</tok-starts-with>
      <ana><!--CIrculi Circuli circuli circulique-->
         <tok val="[C]?(i|I|ci)rculi(que)?"/>
         <lm>
            <l>circulus</l>
            <m cert="0.333333333333333333">n - - p - - - m n</m>
            <m cert="0.333333333333333333">n - - p - - - m v</m>
            <m cert="0.333333333333333333">n - - s - - - m g</m>
         </lm>
      </ana>
      <ana><!--Circulare circulare circularen-->
         <tok val="[cC]irculare[n]?"/>
         <lm cert="0.333333333333333333">
            <l>circularis</l>
            <m cert="0.333333333333333333">a - - s - - - n n</m>
            <m cert="0.333333333333333333">a - - s - - - n a</m>
            <m cert="0.333333333333333333">a - - s - - - n v</m>
         </lm>
         <lm cert="0.333333333333333333">
            <l>circulo</l>
            <m>v - - - p n a</m>
         </lm>
         <lm cert="0.333333333333333333">
            <l>circulor</l>
            <m>v - 2 s p m p</m>
         </lm>
      </ana>
      <ana><!--Circulare Circularis circulare circularen circularis-->
         <tok val="[cC]ircular[e]?(n|is|e)?"/>
         <lm>
            <l>circulor</l>
            <m>v - 2 s p i p</m>
         </lm>
      </ana>
      <ana><!--Circularem circularem-->
         <tok val="[cC]ircularem"/>
         <lm cert="0.5">
            <l>circularis</l>
            <m cert="0.5">a - - s - - - f a</m>
            <m cert="0.5">a - - s - - - m a</m>
         </lm>
         <lm cert="0.5">
            <l>circulo</l>
            <m>v - 1 s i s a</m>
         </lm>
      </ana>
      <ana><!--Circulari circulari circularique-->
         <tok val="[cC]irculari(que)?"/>
         <lm cert="0.5">
            <l>circularis</l>
            <m cert="0.166666666666666667">a - - s - - - n b</m>
            <m cert="0.166666666666666667">a - - s - - - m d</m>
            <m cert="0.166666666666666667">a - - s - - - f d</m>
            <m cert="0.166666666666666667">a - - s - - - n d</m>
            <m cert="0.166666666666666667">a - - s - - - m b</m>
            <m cert="0.166666666666666667">a - - s - - - f b</m>
         </lm>
         <lm cert="0.5">
            <l>circulor</l>
            <m>v - - - p n p</m>
         </lm>
      </ana>
      <ana><!--Circularibus circularibus-->
         <tok val="[cC]ircularibus"/>
         <lm>
            <l>circularis</l>
            <m cert="0.166666666666666667">a - - p - - - n d</m>
            <m cert="0.166666666666666667">a - - p - - - f b</m>
            <m cert="0.166666666666666667">a - - p - - - f d</m>
            <m cert="0.166666666666666667">a - - p - - - m d</m>
            <m cert="0.166666666666666667">a - - p - - - m b</m>
            <m cert="0.166666666666666667">a - - p - - - n b</m>
         </lm>
      </ana>
      <ana><!--Circularis circularis-->
         <tok val="[cC]ircularis"/>
         <lm cert="0.5">
            <l>circulor</l>
            <m>v - 2 s r s a</m>
         </lm>
         <lm cert="0.5">
            <l>circularis</l>
            <m cert="0.142857142857142857">a - - s - - - f g</m>
            <m cert="0.142857142857142857">a - - s - - - m g</m>
            <m cert="0.142857142857142857">a - - s - - - f n</m>
            <m cert="0.142857142857142857">a - - s - - - f v</m>
            <m cert="0.142857142857142857">a - - s - - - m n</m>
            <m cert="0.142857142857142857">a - - s - - - m v</m>
            <m cert="0.142857142857142857">a - - s - - - n g</m>
         </lm>
      </ana>
      <ana><!--Circularis circularen circulares circularis-->
         <tok val="[cC]ircular[e]?(s|n|is)"/>
         <lm>
            <l>circularis</l>
            <m cert="0.5">a - - p - - - m a</m>
            <m cert="0.5">a - - p - - - f a</m>
         </lm>
      </ana>
      <ana><!--Circulatim circulatim-->
         <tok val="[cC]irculatim"/>
         <lm>
            <l>circulatim</l>
            <m>d</m>
         </lm>
      </ana>
      <ana><!--Circulator circulator-->
         <tok val="[cC]irculator"/>
         <lm>
            <l>circulator</l>
            <m cert="0.5">n - - s - - - m n</m>
            <m cert="0.5">n - - s - - - m v</m>
         </lm>
      </ana>
      <ana>
         <tok val="Circulatoria"/>
         <lm>
            <l>circulatorius</l>
            <m cert="0.166666666666666667">a - - s - - - f n</m>
            <m cert="0.166666666666666667">a - - p - - - n n</m>
            <m cert="0.166666666666666667">a - - s - - - f v</m>
            <m cert="0.166666666666666667">a - - p - - - n v</m>
            <m cert="0.166666666666666667">a - - p - - - n a</m>
            <m cert="0.166666666666666667">a - - s - - - f b</m>
         </lm>
      </ana>
      <ana><!--Circulatorius circulatorius-->
         <tok val="[cC]irculatorius"/>
         <lm>
            <l>circulatorius</l>
            <m>a - - s - - - m n</m>
         </lm>
      </ana>
      <ana><!--Circulatrix circulatrix-->
         <tok val="[cC]irculatrix"/>
         <lm>
            <l>circulatrix</l>
            <m cert="0.5">n - - s - - - f n</m>
            <m cert="0.5">n - - s - - - f v</m>
         </lm>
      </ana>
      <ana><!--Circulis circulis-->
         <tok val="[cC]irculis"/>
         <lm>
            <l>circulus</l>
            <m cert="0.5">n - - p - - - m b</m>
            <m cert="0.5">n - - p - - - m d</m>
         </lm>
      </ana>
      <ana><!--Circulo circulo circuloque circuloue-->
         <tok val="[cC]irculo[q]?(ue)?"/>
         <lm cert="0.5">
            <l>circulo</l>
            <m>v - 1 s p i a</m>
         </lm>
         <lm cert="0.5">
            <l>circulus</l>
            <m cert="0.5">n - - s - - - m b</m>
            <m cert="0.5">n - - s - - - m d</m>
         </lm>
      </ana>
      <ana><!--Circulorum Circulum circulorum circulorumque circulum circulumque-->
         <tok val="[cC]ircul(or)?um(que)?"/>
         <lm>
            <l>circulus</l>
            <m>n - - p - - - m g</m>
         </lm>
      </ana>
      <ana><!--Circulos circulos-->
         <tok val="[cC]irculos"/>
         <lm>
            <l>circulus</l>
            <m>n - - p - - - m a</m>
         </lm>
      </ana>
      <ana><!--Circulum circulum circulumque-->
         <tok val="[cC]irculum(que)?"/>
         <lm>
            <l>circulus</l>
            <m>n - - s - - - m a</m>
         </lm>
      </ana>
      <ana><!--Circulus circulus-->
         <tok val="[cC]irculus"/>
         <lm>
            <l>circulus</l>
            <m>n - - s - - - m n</m>
         </lm>
      </ana>
      <ana>
         <tok val="circula"/>
         <lm>
            <l>circulo</l>
            <m>v - 2 s p m a</m>
         </lm>
      </ana>
      <ana>
         <tok val="circulans"/>
         <lm>
            <l>circulor</l>
            <m cert="0.142857142857142857">v - - s p p a m n</m>
            <m cert="0.142857142857142857">v - - s p p a f v</m>
            <m cert="0.142857142857142857">v - - s p p a m v</m>
            <m cert="0.142857142857142857">v - - s p p a n a</m>
            <m cert="0.142857142857142857">v - - s p p a f n</m>
            <m cert="0.142857142857142857">v - - s p p a n n</m>
            <m cert="0.142857142857142857">v - - s p p a n v</m>
         </lm>
      </ana>
      <ana>
         <tok val="circulantem"/>
         <lm>
            <l>circulor</l>
            <m cert="0.5">v - - s p p a f a</m>
            <m cert="0.5">v - - s p p a m a</m>
         </lm>
      </ana>
      <ana>
         <tok val="circulanti"/>
         <lm>
            <l>circulor</l>
            <m cert="0.166666666666666667">v - - s p p a f d</m>
            <m cert="0.166666666666666667">v - - s p p a n d</m>
            <m cert="0.166666666666666667">v - - s p p a m b</m>
            <m cert="0.166666666666666667">v - - s p p a n b</m>
            <m cert="0.166666666666666667">v - - s p p a f b</m>
            <m cert="0.166666666666666667">v - - s p p a m d</m>
         </lm>
      </ana>
      <ana>
         <tok val="circulantur"/>
         <lm>
            <l>circulor</l>
            <m>v - 3 p p i p</m>
         </lm>
      </ana>
      <ana><!--circularen circulares-->
         <tok val="circulare[sn]"/>
         <lm cert="0.5">
            <l>circularis</l>
            <m cert="0.25">a - - p - - - f n</m>
            <m cert="0.25">a - - p - - - f v</m>
            <m cert="0.25">a - - p - - - m v</m>
            <m cert="0.25">a - - p - - - m n</m>
         </lm>
         <lm cert="0.5">
            <l>circulo</l>
            <m>v - 2 s i s a</m>
         </lm>
      </ana>
      <ana>
         <tok val="circularia"/>
         <lm>
            <l>circularis</l>
            <m cert="0.333333333333333333">a - - p - - - n n</m>
            <m cert="0.333333333333333333">a - - p - - - n v</m>
            <m cert="0.333333333333333333">a - - p - - - n a</m>
         </lm>
      </ana>
      <ana>
         <tok val="circulariter"/>
         <lm>
            <l>circularis</l>
            <m>d</m>
         </lm>
      </ana>
      <ana>
         <tok val="circularium"/>
         <lm>
            <l>circularis</l>
            <m cert="0.333333333333333333">a - - p - - - n g</m>
            <m cert="0.333333333333333333">a - - p - - - m g</m>
            <m cert="0.333333333333333333">a - - p - - - f g</m>
         </lm>
      </ana>
      <ana>
         <tok val="circulas"/>
         <lm>
            <l>circulo</l>
            <m>v - 2 s p i a</m>
         </lm>
      </ana>
      <ana>
         <tok val="circulata"/>
         <lm>
            <l>circulor</l>
            <m cert="0.166666666666666667">v - - p r p p n a</m>
            <m cert="0.166666666666666667">v - - s r p p f b</m>
            <m cert="0.166666666666666667">v - - s r p p f n</m>
            <m cert="0.166666666666666667">v - - p r p p n v</m>
            <m cert="0.166666666666666667">v - - s r p p f v</m>
            <m cert="0.166666666666666667">v - - p r p p n n</m>
         </lm>
      </ana>
      <ana>
         <tok val="circulati"/>
         <lm>
            <l>circulor</l>
            <m cert="0.25">v - - s r p p n g</m>
            <m cert="0.25">v - - p r p p m v</m>
            <m cert="0.25">v - - p r p p m n</m>
            <m cert="0.25">v - - s r p p m g</m>
         </lm>
      </ana>
      <ana>
         <tok val="circulatio"/>
         <lm>
            <l>circulatio</l>
            <m cert="0.5">n - - s - - - f n</m>
            <m cert="0.5">n - - s - - - f v</m>
         </lm>
      </ana>
      <ana>
         <tok val="circulatione"/>
         <lm>
            <l>circulatio</l>
            <m>n - - s - - - f b</m>
         </lm>
      </ana>
      <ana>
         <tok val="circulationem"/>
         <lm>
            <l>circulatio</l>
            <m>n - - s - - - f a</m>
         </lm>
      </ana>
      <ana><!--circulationes circulationesve-->
         <tok val="circulationes(ve)?"/>
         <lm>
            <l>circulatio</l>
            <m cert="0.333333333333333333">n - - p - - - f v</m>
            <m cert="0.333333333333333333">n - - p - - - f a</m>
            <m cert="0.333333333333333333">n - - p - - - f n</m>
         </lm>
      </ana>
      <ana>
         <tok val="circulationibus"/>
         <lm>
            <l>circulatio</l>
            <m cert="0.5">n - - p - - - f b</m>
            <m cert="0.5">n - - p - - - f d</m>
         </lm>
      </ana>
      <ana>
         <tok val="circulationis"/>
         <lm>
            <l>circulatio</l>
            <m>n - - s - - - f g</m>
         </lm>
      </ana>
      <ana>
         <tok val="circulationum"/>
         <lm>
            <l>circulatio</l>
            <m>n - - p - - - f g</m>
         </lm>
      </ana>
      <ana>
         <tok val="circulatis"/>
         <lm cert="0.5">
            <l>circulo</l>
            <m>v - 2 p p i a</m>
         </lm>
         <lm cert="0.5">
            <l>circulor</l>
            <m cert="0.166666666666666667">v - - p r p p n d</m>
            <m cert="0.166666666666666667">v - - p r p p f d</m>
            <m cert="0.166666666666666667">v - - p r p p n b</m>
            <m cert="0.166666666666666667">v - - p r p p m d</m>
            <m cert="0.166666666666666667">v - - p r p p f b</m>
            <m cert="0.166666666666666667">v - - p r p p m b</m>
         </lm>
      </ana>
      <ana>
         <tok val="circulato"/>
         <lm cert="0.5">
            <l>circulor</l>
            <m cert="0.25">v - - s r p p n d</m>
            <m cert="0.25">v - - s r p p n b</m>
            <m cert="0.25">v - - s r p p m b</m>
            <m cert="0.25">v - - s r p p m d</m>
         </lm>
         <lm cert="0.5">
            <l>circulo</l>
            <m cert="0.5">v - 2 s f m a</m>
            <m cert="0.5">v - 3 s f m a</m>
         </lm>
      </ana>
      <ana>
         <tok val="circulatore"/>
         <lm>
            <l>circulator</l>
            <m>n - - s - - - m b</m>
         </lm>
      </ana>
      <ana>
         <tok val="circulatorem"/>
         <lm>
            <l>circulator</l>
            <m>n - - s - - - m a</m>
         </lm>
      </ana>
      <ana>
         <tok val="circulatores"/>
         <lm>
            <l>circulator</l>
            <m cert="0.333333333333333333">n - - p - - - m n</m>
            <m cert="0.333333333333333333">n - - p - - - m v</m>
            <m cert="0.333333333333333333">n - - p - - - m a</m>
         </lm>
      </ana>
      <ana>
         <tok val="circulatoriae"/>
         <lm>
            <l>circulatorius</l>
            <m cert="0.25">a - - p - - - f v</m>
            <m cert="0.25">a - - p - - - f n</m>
            <m cert="0.25">a - - s - - - f d</m>
            <m cert="0.25">a - - s - - - f g</m>
         </lm>
      </ana>
      <ana>
         <tok val="circulatoriam"/>
         <lm>
            <l>circulatorius</l>
            <m>a - - s - - - f a</m>
         </lm>
      </ana>
      <ana>
         <tok val="circulatoribus"/>
         <lm>
            <l>circulator</l>
            <m cert="0.5">n - - p - - - m b</m>
            <m cert="0.5">n - - p - - - m d</m>
         </lm>
      </ana>
      <ana>
         <tok val="circulatoriis"/>
         <lm>
            <l>circulatorius</l>
            <m cert="0.166666666666666667">a - - p - - - n d</m>
            <m cert="0.166666666666666667">a - - p - - - f b</m>
            <m cert="0.166666666666666667">a - - p - - - f d</m>
            <m cert="0.166666666666666667">a - - p - - - m d</m>
            <m cert="0.166666666666666667">a - - p - - - n b</m>
            <m cert="0.166666666666666667">a - - p - - - m b</m>
         </lm>
      </ana>
      <ana>
         <tok val="circulatricis"/>
         <lm>
            <l>circulatrix</l>
            <m>n - - s - - - f g</m>
         </lm>
      </ana>
      <ana>
         <tok val="circulatum"/>
         <lm>
            <l>circulor</l>
            <m cert="0.142857142857142857">v - - p r p p m g</m>
            <m cert="0.142857142857142857">v - - p r p p n g</m>
            <m cert="0.142857142857142857">v - - s r p p n n</m>
            <m cert="0.142857142857142857">v - - s r p p n v</m>
            <m cert="0.142857142857142857">v - - s r p p n a</m>
            <m cert="0.142857142857142857">v - - s r p p m a</m>
            <m cert="0.142857142857142857">v - - - - u - - a</m>
         </lm>
      </ana>
      <ana>
         <tok val="circulatus"/>
         <lm>
            <l>circulor</l>
            <m>v - - s r p p m n</m>
         </lm>
      </ana>
      <ana>
         <tok val="circulor"/>
         <lm>
            <l>circulor</l>
            <m>v - 1 s p i p</m>
         </lm>
      </ana>
      <ana>
         <tok val="circulauerat"/>
         <lm cert="0.5">
            <l>circulor</l>
            <m>v - 3 s l i a</m>
         </lm>
         <lm cert="0.5">
            <l>circulo</l>
            <m>v - 3 s l i a</m>
         </lm>
      </ana>
   </body>
</TAN-A-lm>
