<?xml version="1.0" encoding="UTF-8"?>
<?xml-model href="../../../TAN-2018/schemas/TAN-A-lm.rnc" type="application/relax-ng-compact-syntax"?>
<?xml-model href="../../../TAN-2018/schemas/TAN-A-lm.sch" type="application/xml" schematypens="http://purl.oclc.org/dsdl/schematron"?>
<TAN-A-lm xmlns="tag:textalign.net,2015:ns"
          TAN-version="2018"
          id="tag:kalvesmaki.com,2015:tan-a-lm:lat:perseusfem">
   <head>
      <name>Perseus lexico-morphological permutations devoted exclusively to fem</name>
      <master-location href="https://raw.githubusercontent.com/Arithmeticus/TAN-lexico-morphology/master/lat/lm-perseus/lat-tan-a-lm-fem.xml"/>
      <license which="Attribution-ShareAlike 3.0 Unported"/>
      <licensor who="perseus"/>
      <key>
         <IRI>tag:kalvesmaki.com,2014:tan-key:lm</IRI>
         <name>General keywords associated with Kalvesmaki's collection of lexico-morphology files</name>
         <location href="../../lm.TAN-key.xml" when-accessed="2018-03-24"/>
      </key>
      <definitions>
         <lexicon xml:id="LS" which="Lewis and Short"/>
         <morphology xml:id="perseus-dik" which="Perseus Latin morphology"/>
         <organization xml:id="perseus" which="Perseus Project"/>
         <person xml:id="dik" which="Helma Dik"/>
         <person xml:id="kalvesmaki" which="Joel Kalvesmaki"/>
         <role which="creator" xml:id="creator"/>
         <role which="sponsor" xml:id="sponsor"/>
         <role which="editor" xml:id="editor"/>
      </definitions>
      <resp who="perseus dik" roles="creator"/>
      <resp who="perseus" roles="sponsor"/>
      <resp who="kalvesmaki" roles="editor"/>
      <change when="2018-01-11" who="kalvesmaki">Started template file.</change>
      <change who="kalvesmaki" when="2018-03-24">Cleaned file for publication.</change>
   </head>
   <body lexicon="LS" morphology="perseus-dik">
      <for-lang>lat</for-lang>
      <tok-starts-with>FEM</tok-starts-with>
      <tok-starts-with>Fem</tok-starts-with>
      <tok-starts-with>fem</tok-starts-with>
      <tok-starts-with>fém</tok-starts-with>
      <ana><!--FEMINA Femina femina feminaque feminast feminaue fémina-->
         <tok val="[fF]?(e|fé)?(mina)?[q]?(ue|st|FEMINA)?"/>
         <lm>
            <l>femina</l>
            <m>n - - s - - - f b</m>
         </lm>
      </ana>
      <ana><!--FEMINA Femina femina feminaque feminast feminaue-->
         <tok val="[fF]?(emina)?[q]?(ue|st|FEMINA)?"/>
         <lm cert="0.5">
            <l>femina</l>
            <m cert="0.5">n - - s - - - f n</m>
            <m cert="0.5">n - - s - - - f v</m>
         </lm>
         <lm cert="0.5">
            <l>femino</l>
            <m>v - 2 s p m a</m>
         </lm>
      </ana>
      <ana><!--Feminae feminae feminaeque-->
         <tok val="[fF]eminae(que)?"/>
         <lm>
            <l>femina</l>
            <m cert="0.25">n - - p - - - f v</m>
            <m cert="0.25">n - - s - - - f g</m>
            <m cert="0.25">n - - p - - - f n</m>
            <m cert="0.25">n - - s - - - f d</m>
         </lm>
      </ana>
      <ana><!--Feminam feminam feminamque-->
         <tok val="[fF]eminam(que)?"/>
         <lm>
            <l>femina</l>
            <m>n - - s - - - f a</m>
         </lm>
      </ana>
      <ana><!--Feminarum feminarum feminarumque feminarumve feminárum-->
         <tok val="[fF]emin[aá]rum(ve|que)?"/>
         <lm>
            <l>femina</l>
            <m>n - - p - - - f g</m>
         </lm>
      </ana>
      <ana><!--Feminas feminas feminasque feminasve-->
         <tok val="[fF]eminas(ve|que)?"/>
         <lm cert="0.5">
            <l>femino</l>
            <m>v - 2 s p i a</m>
         </lm>
         <lm cert="0.5">
            <l>femina</l>
            <m>n - - p - - - f a</m>
         </lm>
      </ana>
      <ana><!--Feminea feminea-->
         <tok val="[fF]eminea"/>
         <lm>
            <l>femineus</l>
            <m cert="0.166666666666666667">a - - s - - - f n</m>
            <m cert="0.166666666666666667">a - - p - - - n n</m>
            <m cert="0.166666666666666667">a - - s - - - f v</m>
            <m cert="0.166666666666666667">a - - p - - - n v</m>
            <m cert="0.166666666666666667">a - - p - - - n a</m>
            <m cert="0.166666666666666667">a - - s - - - f b</m>
         </lm>
      </ana>
      <ana><!--Femineae femineae-->
         <tok val="[fF]emineae"/>
         <lm>
            <l>femineus</l>
            <m cert="0.25">a - - p - - - f v</m>
            <m cert="0.25">a - - p - - - f n</m>
            <m cert="0.25">a - - s - - - f d</m>
            <m cert="0.25">a - - s - - - f g</m>
         </lm>
      </ana>
      <ana><!--Femineam femineam-->
         <tok val="[fF]emineam"/>
         <lm>
            <l>femineus</l>
            <m>a - - s - - - f a</m>
         </lm>
      </ana>
      <ana><!--Femineas femineas-->
         <tok val="[fF]emineas"/>
         <lm>
            <l>femineus</l>
            <m>a - - p - - - f a</m>
         </lm>
      </ana>
      <ana><!--Feminei feminei-->
         <tok val="[fF]eminei"/>
         <lm>
            <l>femineus</l>
            <m cert="0.25">a - - s - - - m g</m>
            <m cert="0.25">a - - p - - - m v</m>
            <m cert="0.25">a - - p - - - m n</m>
            <m cert="0.25">a - - s - - - n g</m>
         </lm>
      </ana>
      <ana><!--Femineis femineis-->
         <tok val="[fF]emineis"/>
         <lm>
            <l>femineus</l>
            <m cert="0.166666666666666667">a - - p - - - n d</m>
            <m cert="0.166666666666666667">a - - p - - - f b</m>
            <m cert="0.166666666666666667">a - - p - - - f d</m>
            <m cert="0.166666666666666667">a - - p - - - m d</m>
            <m cert="0.166666666666666667">a - - p - - - n b</m>
            <m cert="0.166666666666666667">a - - p - - - m b</m>
         </lm>
      </ana>
      <ana><!--Femineo femineo-->
         <tok val="[fF]emineo"/>
         <lm>
            <l>femineus</l>
            <m cert="0.25">a - - s - - - n b</m>
            <m cert="0.25">a - - s - - - m d</m>
            <m cert="0.25">a - - s - - - n d</m>
            <m cert="0.25">a - - s - - - m b</m>
         </lm>
      </ana>
      <ana><!--Femineum femineum femineumque-->
         <tok val="[fF]emineum(que)?"/>
         <lm>
            <l>femineus</l>
            <m cert="0.166666666666666667">a - - s - - - n n</m>
            <m cert="0.166666666666666667">a - - p - - - n g</m>
            <m cert="0.166666666666666667">a - - s - - - n a</m>
            <m cert="0.166666666666666667">a - - s - - - n v</m>
            <m cert="0.166666666666666667">a - - p - - - m g</m>
            <m cert="0.166666666666666667">a - - s - - - m a</m>
         </lm>
      </ana>
      <ana><!--Femineus femineus femineusque-->
         <tok val="[fF]emineus(que)?"/>
         <lm>
            <l>femineus</l>
            <m>a - - s - - - m n</m>
         </lm>
      </ana>
      <ana><!--Feminino feminino-->
         <tok val="[fF]eminino"/>
         <lm>
            <l>femininus</l>
            <m cert="0.25">a - - s - - - n b</m>
            <m cert="0.25">a - - s - - - m d</m>
            <m cert="0.25">a - - s - - - n d</m>
            <m cert="0.25">a - - s - - - m b</m>
         </lm>
      </ana>
      <ana><!--Feminis feminis feminisque-->
         <tok val="[fF]eminis(que)?"/>
         <lm>
            <l>femina</l>
            <m cert="0.5">n - - p - - - f b</m>
            <m cert="0.5">n - - p - - - f d</m>
         </lm>
      </ana>
      <ana><!--Femur femur femurque-->
         <tok val="[fF]emur(que)?"/>
         <lm>
            <l>for</l>
            <m>v - 1 p p s p</m>
         </lm>
      </ana>
      <ana>
         <tok val="fem"/>
         <lm>
            <l>for</l>
            <m>v - 1 s p s a</m>
         </lm>
      </ana>
      <ana>
         <tok val="femella"/>
         <lm>
            <l>femella</l>
            <m cert="0.333333333333333333">n - - s - - - f b</m>
            <m cert="0.333333333333333333">n - - s - - - f n</m>
            <m cert="0.333333333333333333">n - - s - - - f v</m>
         </lm>
      </ana>
      <ana>
         <tok val="femellarius"/>
         <lm>
            <l>femellarius</l>
            <m>n - - s - - - m n</m>
         </lm>
      </ana>
      <ana>
         <tok val="femellas"/>
         <lm>
            <l>femella</l>
            <m>n - - p - - - f a</m>
         </lm>
      </ana>
      <ana>
         <tok val="feminal"/>
         <lm>
            <l>feminal</l>
            <m>n - - s - - - n n</m>
         </lm>
      </ana>
      <ana>
         <tok val="feminalia"/>
         <lm>
            <l>feminalia</l>
            <m cert="0.333333333333333333">n - - p - - - n a</m>
            <m cert="0.333333333333333333">n - - p - - - n v</m>
            <m cert="0.333333333333333333">n - - p - - - n n</m>
         </lm>
      </ana>
      <ana>
         <tok val="feminalibus"/>
         <lm>
            <l>feminal</l>
            <m cert="0.5">n - - p - - - n d</m>
            <m cert="0.5">n - - p - - - n b</m>
         </lm>
      </ana>
      <ana>
         <tok val="feminatus"/>
         <lm cert="0.5">
            <l>femino</l>
            <m>v - - s r p p m n</m>
         </lm>
         <lm cert="0.5">
            <l>feminatus</l>
            <m>a - - s - - - m n</m>
         </lm>
      </ana>
      <ana>
         <tok val="femineos"/>
         <lm>
            <l>femineus</l>
            <m>a - - p - - - m a</m>
         </lm>
      </ana>
      <ana>
         <tok val="femini"/>
         <lm>
            <l>for</l>
            <m>v - 2 p p s p</m>
         </lm>
      </ana>
      <ana>
         <tok val="feminina"/>
         <lm>
            <l>femininus</l>
            <m cert="0.166666666666666667">a - - s - - - f n</m>
            <m cert="0.166666666666666667">a - - p - - - n n</m>
            <m cert="0.166666666666666667">a - - s - - - f v</m>
            <m cert="0.166666666666666667">a - - p - - - n a</m>
            <m cert="0.166666666666666667">a - - p - - - n v</m>
            <m cert="0.166666666666666667">a - - s - - - f b</m>
         </lm>
      </ana>
      <ana>
         <tok val="feminine"/>
         <lm>
            <l>femininus</l>
            <m cert="0.5">d</m>
            <m cert="0.5">a - - s - - - m v</m>
         </lm>
      </ana>
      <ana><!--feminine femininum femininumque femininumve-->
         <tok val="feminin(um)?(ve|que|e)?"/>
         <lm>
            <l>femininus</l>
            <m>a - - s - - - n v</m>
         </lm>
      </ana>
      <ana>
         <tok val="feminini"/>
         <lm>
            <l>femininus</l>
            <m cert="0.25">a - - s - - - m g</m>
            <m cert="0.25">a - - p - - - m v</m>
            <m cert="0.25">a - - p - - - m n</m>
            <m cert="0.25">a - - s - - - n g</m>
         </lm>
      </ana>
      <ana>
         <tok val="femininis"/>
         <lm>
            <l>femininus</l>
            <m cert="0.166666666666666667">a - - p - - - n d</m>
            <m cert="0.166666666666666667">a - - p - - - f b</m>
            <m cert="0.166666666666666667">a - - p - - - f d</m>
            <m cert="0.166666666666666667">a - - p - - - m d</m>
            <m cert="0.166666666666666667">a - - p - - - m b</m>
            <m cert="0.166666666666666667">a - - p - - - n b</m>
         </lm>
      </ana>
      <ana><!--femininum femininumque femininumve-->
         <tok val="femininum(ve|que)?"/>
         <lm>
            <l>femininus</l>
            <m cert="0.2">a - - s - - - n n</m>
            <m cert="0.2">a - - s - - - n a</m>
            <m cert="0.2">a - - p - - - n g</m>
            <m cert="0.2">a - - p - - - m g</m>
            <m cert="0.2">a - - s - - - m a</m>
         </lm>
      </ana>
      <ana>
         <tok val="femininus"/>
         <lm>
            <l>femininus</l>
            <m>a - - s - - - m n</m>
         </lm>
      </ana>
      <ana>
         <tok val="femino"/>
         <lm>
            <l>femino</l>
            <m>v - 1 s p i a</m>
         </lm>
      </ana>
      <ana>
         <tok val="femorale"/>
         <lm>
            <l>femorale</l>
            <m cert="0.25">n - - s - - - n a</m>
            <m cert="0.25">n - - s - - - n v</m>
            <m cert="0.25">n - - s - - - n b</m>
            <m cert="0.25">n - - s - - - n n</m>
         </lm>
      </ana>
      <ana>
         <tok val="femoralia"/>
         <lm>
            <l>femorale</l>
            <m cert="0.333333333333333333">n - - p - - - n a</m>
            <m cert="0.333333333333333333">n - - p - - - n v</m>
            <m cert="0.333333333333333333">n - - p - - - n n</m>
         </lm>
      </ana>
      <ana>
         <tok val="femoralis"/>
         <lm>
            <l>femorale</l>
            <m>n - - s - - - n g</m>
         </lm>
      </ana>
      <ana>
         <tok val="femore"/>
         <lm>
            <l>femur</l>
            <m>n - - s - - - n b</m>
         </lm>
      </ana>
      <ana><!--femus femusque-->
         <tok val="femus(que)?"/>
         <lm>
            <l>for</l>
            <m>v - 1 p p s a</m>
         </lm>
      </ana>
      <ana>
         <tok val="femine"/>
         <lm>
            <l>femur</l>
            <m>n - - s - - - m b</m>
         </lm>
      </ana>
      <ana><!--feminibus feminibusque-->
         <tok val="feminibus(que)?"/>
         <lm>
            <l>femur</l>
            <m cert="0.5">n - - p - - - m b</m>
            <m cert="0.5">n - - p - - - m d</m>
         </lm>
      </ana>
      <ana>
         <tok val="feminum"/>
         <lm>
            <l>femur</l>
            <m>n - - p - - - m g</m>
         </lm>
      </ana>
   </body>
</TAN-A-lm>
