<?xml version="1.0" encoding="UTF-8"?>
<?xml-model href="../../../../../TAN-2020/schemas/TAN-A-lm.rnc" type="application/relax-ng-compact-syntax"?>
<?xml-model href="../../../../../TAN-2020/schemas/TAN-A-lm.sch" type="application/xml" schematypens="http://purl.oclc.org/dsdl/schematron"?>
<TAN-A-lm xmlns="tag:textalign.net,2015:ns"
          TAN-version="2020"
          id="tag:kalvesmaki.com,2015:tan-a-lm:lat:perseus:supers">
   <head>
      <name>Perseus lexico-morphological permutations devoted exclusively to supers</name>
      <master-location href="https://raw.githubusercontent.com/Arithmeticus/TAN-lexico-morphology/master/lat/lm-perseus/lat-tan-a-lm-supers.xml"/>
      <license which="Attribution-ShareAlike 3.0 Unported" licensor="perseus"/>
      <for-lang>lat</for-lang>
      <tok-starts-with>Supers</tok-starts-with>
      <tok-starts-with>supers</tok-starts-with>
      <vocabulary>
         <IRI>tag:kalvesmaki.com,2014:tan-key:lm</IRI>
         <name>General keywords associated with Kalvesmaki's collection of lexico-morphology
                files</name>
         <location href="../../lm.TAN-voc.xml" accessed-when="2018-03-24"/>
      </vocabulary>
      <vocabulary-key>
         <algorithm xml:id="xslt1">
            <IRI>tag:textalign.net,2015:stylesheet:convert:perseus-raw-xml-to-tan-a-lm</IRI>
            <name>An unnamed stylesheet</name>
            <location href="../../../TAN-2020/applications/convert/private-convert%20perseus%20raw%20xml%20to%20TAN-A-lm.xsl"
                      accessed-when="2019-04-29T04:48:11.777-04:00"/>
         </algorithm>
         <role xml:id="stylesheet" which="stylesheet"/>
         <lexicon xml:id="LS" which="Lewis and Short"/>
         <morphology xml:id="perseus-dik"
                     which="Perseus Latin morphology"
                     accessed-when="2020-03-05"/>
         <organization xml:id="perseus" which="Perseus Project"/>
         <person xml:id="dik" which="Helma Dik"/>
         <person xml:id="kalvesmaki" which="Joel Kalvesmaki"/>
      </vocabulary-key>
      <file-resp who="kalvesmaki"/>
      <resp who="xslt1" roles="stylesheet"/>
      <resp who="perseus dik" roles="creator"/>
      <resp who="perseus" roles="sponsor"/>
      <change when="2018-01-11" who="kalvesmaki">Started template file.</change>
      <change who="xslt1" when="2019-04-29T04:48:11.777-04:00">Created TAN-A-lm from file:/E:/Joel/Dropbox/TAN/pre-TAN/language-specific%20morphology/lat/LatinMorph16-supers.xml</change>
      <to-do/>
   </head>
   <body lexicon="LS" morphology="perseus-dik" claimant="xslt1">
      <ana>
         <tok val="Superscando"/>
         <tok val="superscando"/>
         <lm>
            <l>superscando</l>
            <m>v - 1 s p i a</m>
         </lm>
      </ana>
      <ana>
         <tok val="Superscribo"/>
         <tok val="superscribo"/>
         <lm>
            <l>superscribo</l>
            <m>v - 1 s p i a</m>
         </lm>
      </ana>
      <ana>
         <tok val="Supersede"/>
         <tok val="supersede"/>
         <tok val="superseden"/>
         <lm>
            <l>supersedeo</l>
            <m>v - 2 s p m a</m>
         </lm>
      </ana>
      <ana>
         <tok val="Supersedeas"/>
         <tok val="supersedeas"/>
         <lm>
            <l>supersedeo</l>
            <m>v - 2 s p s a</m>
         </lm>
      </ana>
      <ana>
         <tok val="Supersedeo"/>
         <tok val="supersedeo"/>
         <lm>
            <l>supersedeo</l>
            <m>v - 1 s p i a</m>
         </lm>
      </ana>
      <ana>
         <tok val="Supersedi"/>
         <tok val="supersedi"/>
         <lm>
            <l>supersedeo</l>
            <m>v - 1 s r i a</m>
         </lm>
      </ana>
      <ana>
         <tok val="Supersint"/>
         <tok val="supersint"/>
         <lm>
            <l>supersum</l>
            <m>v - 3 p p s a</m>
         </lm>
      </ana>
      <ana>
         <tok val="Superspargo"/>
         <tok val="superspargo"/>
         <lm>
            <l>superspargo</l>
            <m>v - 1 s p i a</m>
         </lm>
      </ana>
      <ana>
         <tok val="Superstagno"/>
         <tok val="superstagno"/>
         <lm>
            <l>superstagno</l>
            <m>v - 1 s p i a</m>
         </lm>
      </ana>
      <ana>
         <tok val="Supersterno"/>
         <tok val="supersterno"/>
         <lm>
            <l>supersterno</l>
            <m>v - 1 s p i a</m>
         </lm>
      </ana>
      <ana>
         <tok val="Superstes"/>
         <tok val="superstes"/>
         <lm>
            <l>supersto</l>
            <m>v - 2 s p s a</m>
         </lm>
      </ana>
      <ana>
         <tok val="Superstite"/>
         <tok val="superstate"/>
         <tok val="superstite"/>
         <lm>
            <l>supersto</l>
            <m>v - - s r p p m v</m>
         </lm>
      </ana>
      <ana>
         <tok val="Superstite"/>
         <tok val="superstate"/>
         <tok val="superstite"/>
         <tok val="superstitum"/>
         <lm>
            <l>supersto</l>
            <m>v - - s r p p n v</m>
         </lm>
      </ana>
      <ana>
         <tok val="Superstitem"/>
         <tok val="superstitem"/>
         <lm>
            <l>superstito</l>
            <m>v - 1 s p s a</m>
         </lm>
      </ana>
      <ana>
         <tok val="Superstites"/>
         <tok val="superstites"/>
         <lm>
            <l>superstito</l>
            <m>v - 2 s p s a</m>
         </lm>
      </ana>
      <ana>
         <tok val="Superstitio"/>
         <tok val="superstitio"/>
         <tok val="superstition"/>
         <lm>
            <l>superstitio</l>
            <m cert="0.5">n - - s - - - f n</m>
            <m cert="0.5">n - - s - - - f v</m>
         </lm>
      </ana>
      <ana>
         <tok val="Superstitione"/>
         <tok val="superstitione"/>
         <lm>
            <l>superstitio</l>
            <m>n - - s - - - f b</m>
         </lm>
      </ana>
      <ana>
         <tok val="Superstitiones"/>
         <tok val="superstitiones"/>
         <lm>
            <l>superstitio</l>
            <m cert="0.333333333333333333">n - - p - - - f v</m>
            <m cert="0.333333333333333333">n - - p - - - f a</m>
            <m cert="0.333333333333333333">n - - p - - - f n</m>
         </lm>
      </ana>
      <ana>
         <tok val="Superstitiosa"/>
         <tok val="superstitiosa"/>
         <lm>
            <l>superstitiosus</l>
            <m cert="0.166666666666666667">a - - s - - - f n</m>
            <m cert="0.166666666666666667">a - - p - - - n n</m>
            <m cert="0.166666666666666667">a - - s - - - f v</m>
            <m cert="0.166666666666666667">a - - p - - - n v</m>
            <m cert="0.166666666666666667">a - - p - - - n a</m>
            <m cert="0.166666666666666667">a - - s - - - f b</m>
         </lm>
      </ana>
      <ana>
         <tok val="Superstitiose"/>
         <tok val="superstitiose"/>
         <lm>
            <l>superstitiosus</l>
            <m cert="0.5">d</m>
            <m cert="0.5">a - - s - - - m v</m>
         </lm>
      </ana>
      <ana>
         <tok val="Superstitiose"/>
         <tok val="Superstitiosum"/>
         <tok val="superstitiose"/>
         <tok val="superstitiosum"/>
         <lm>
            <l>superstitiosus</l>
            <m>a - - s - - - n v</m>
         </lm>
      </ana>
      <ana>
         <tok val="Superstitiosum"/>
         <tok val="superstitiosum"/>
         <lm>
            <l>superstitiosus</l>
            <m cert="0.2">a - - s - - - n n</m>
            <m cert="0.2">a - - p - - - n g</m>
            <m cert="0.2">a - - s - - - n a</m>
            <m cert="0.2">a - - p - - - m g</m>
            <m cert="0.2">a - - s - - - m a</m>
         </lm>
      </ana>
      <ana>
         <tok val="Superstitiosus"/>
         <tok val="superstitiosus"/>
         <tok val="superstitiosust"/>
         <lm>
            <l>superstitiosus</l>
            <m>a - - s - - - m n</m>
         </lm>
      </ana>
      <ana>
         <tok val="Superstito"/>
         <tok val="superstito"/>
         <lm>
            <l>superstito</l>
            <m>v - 1 s p i a</m>
         </lm>
      </ana>
      <ana>
         <tok val="Supersto"/>
         <tok val="supersto"/>
         <lm>
            <l>supersto</l>
            <m>v - 1 s p i a</m>
         </lm>
      </ana>
      <ana>
         <tok val="Superstruo"/>
         <tok val="superstruo"/>
         <lm>
            <l>superstruo</l>
            <m>v - 1 s p i a</m>
         </lm>
      </ana>
      <ana>
         <tok val="Supersum"/>
         <tok val="supersum"/>
         <lm>
            <l>supersum</l>
            <m>v - 1 s p i a</m>
         </lm>
      </ana>
      <ana>
         <tok val="Supersunt"/>
         <tok val="supersunt"/>
         <lm>
            <l>supersum</l>
            <m>v - 3 p p i a</m>
         </lm>
      </ana>
      <ana>
         <tok val="superscandens"/>
         <lm>
            <l>superscando</l>
            <m cert="0.142857142857142857">v - - s p p a f v</m>
            <m cert="0.142857142857142857">v - - s p p a m n</m>
            <m cert="0.142857142857142857">v - - s p p a m v</m>
            <m cert="0.142857142857142857">v - - s p p a f n</m>
            <m cert="0.142857142857142857">v - - s p p a n a</m>
            <m cert="0.142857142857142857">v - - s p p a n v</m>
            <m cert="0.142857142857142857">v - - s p p a n n</m>
         </lm>
      </ana>
      <ana>
         <tok val="superscandere"/>
         <lm>
            <l>superscando</l>
            <m cert="0.25">v - - - p n a</m>
            <m cert="0.25">v - 2 s p m p</m>
            <m cert="0.25">v - 2 s p i p</m>
            <m cert="0.25">v - 2 s f i p</m>
         </lm>
      </ana>
      <ana>
         <tok val="superscandis"/>
         <lm>
            <l>superscando</l>
            <m>v - 2 s p i a</m>
         </lm>
      </ana>
      <ana>
         <tok val="superscribam"/>
         <lm>
            <l>superscribo</l>
            <m cert="0.5">v - 1 s p s a</m>
            <m cert="0.5">v - 1 s f i a</m>
         </lm>
      </ana>
      <ana>
         <tok val="superscribere"/>
         <lm>
            <l>superscribo</l>
            <m cert="0.25">v - - - p n a</m>
            <m cert="0.25">v - 2 s p m p</m>
            <m cert="0.25">v - 2 s p i p</m>
            <m cert="0.25">v - 2 s f i p</m>
         </lm>
      </ana>
      <ana>
         <tok val="superscribes"/>
         <lm>
            <l>superscribo</l>
            <m>v - 2 s f i a</m>
         </lm>
      </ana>
      <ana>
         <tok val="superscribis"/>
         <lm>
            <l>superscribo</l>
            <m>v - 2 s p i a</m>
         </lm>
      </ana>
      <ana>
         <tok val="superscripserunt"/>
         <lm>
            <l>superscribo</l>
            <m>v - 3 p r i a</m>
         </lm>
      </ana>
      <ana>
         <tok val="superscripsit"/>
         <lm>
            <l>superscribo</l>
            <m>v - 3 s r i a</m>
         </lm>
      </ana>
      <ana>
         <tok val="superscripta"/>
         <lm>
            <l>superscribo</l>
            <m cert="0.166666666666666667">v - - p r p p n a</m>
            <m cert="0.166666666666666667">v - - s r p p f b</m>
            <m cert="0.166666666666666667">v - - s r p p f n</m>
            <m cert="0.166666666666666667">v - - s r p p f v</m>
            <m cert="0.166666666666666667">v - - p r p p n v</m>
            <m cert="0.166666666666666667">v - - p r p p n n</m>
         </lm>
      </ana>
      <ana>
         <tok val="superscriptae"/>
         <lm>
            <l>superscribo</l>
            <m cert="0.25">v - - s r p p f g</m>
            <m cert="0.25">v - - s r p p f d</m>
            <m cert="0.25">v - - p r p p f n</m>
            <m cert="0.25">v - - p r p p f v</m>
         </lm>
      </ana>
      <ana>
         <tok val="superscriptio"/>
         <tok val="superscription"/>
         <lm>
            <l>superscriptio</l>
            <m cert="0.5">n - - s - - - f n</m>
            <m cert="0.5">n - - s - - - f v</m>
         </lm>
      </ana>
      <ana>
         <tok val="superscriptione"/>
         <lm>
            <l>superscriptio</l>
            <m>n - - s - - - f b</m>
         </lm>
      </ana>
      <ana>
         <tok val="superscriptionem"/>
         <lm>
            <l>superscriptio</l>
            <m>n - - s - - - f a</m>
         </lm>
      </ana>
      <ana>
         <tok val="superscriptiones"/>
         <lm>
            <l>superscriptio</l>
            <m cert="0.333333333333333333">n - - p - - - f v</m>
            <m cert="0.333333333333333333">n - - p - - - f n</m>
            <m cert="0.333333333333333333">n - - p - - - f a</m>
         </lm>
      </ana>
      <ana>
         <tok val="superscriptionibus"/>
         <lm>
            <l>superscriptio</l>
            <m cert="0.5">n - - p - - - f d</m>
            <m cert="0.5">n - - p - - - f b</m>
         </lm>
      </ana>
      <ana>
         <tok val="superscriptum"/>
         <lm>
            <l>superscribo</l>
            <m cert="0.142857142857142857">a - - s - - - n n</m>
            <m cert="0.142857142857142857">v - - p r p p m g</m>
            <m cert="0.142857142857142857">v - - s r p p n n</m>
            <m cert="0.142857142857142857">v - - p r p p n g</m>
            <m cert="0.142857142857142857">v - - s r p p n a</m>
            <m cert="0.142857142857142857">v - - s r p p n v</m>
            <m cert="0.142857142857142857">v - - s r p p m a</m>
         </lm>
      </ana>
      <ana>
         <tok val="supersedeamus"/>
         <lm>
            <l>supersedeo</l>
            <m>v - 1 p p s a</m>
         </lm>
      </ana>
      <ana>
         <tok val="supersedeant"/>
         <lm>
            <l>supersedeo</l>
            <m>v - 3 p p s a</m>
         </lm>
      </ana>
      <ana>
         <tok val="supersedeat"/>
         <lm>
            <l>supersedeo</l>
            <m>v - 3 s p s a</m>
         </lm>
      </ana>
      <ana>
         <tok val="supersedebis"/>
         <lm>
            <l>supersedeo</l>
            <m>v - 2 s f i a</m>
         </lm>
      </ana>
      <ana>
         <tok val="supersedebo"/>
         <lm>
            <l>supersedeo</l>
            <m>v - 1 s f i a</m>
         </lm>
      </ana>
      <ana>
         <tok val="supersedemus"/>
         <lm>
            <l>supersedeo</l>
            <m>v - 1 p p i a</m>
         </lm>
      </ana>
      <ana>
         <tok val="superseden"/>
         <tok val="supersedes"/>
         <lm>
            <l>supersedeo</l>
            <m>v - 2 s p i a</m>
         </lm>
      </ana>
      <ana>
         <tok val="supersedenda"/>
         <lm>
            <l>supersedeo</l>
            <m cert="0.166666666666666667">v - - s p g p f b</m>
            <m cert="0.166666666666666667">v - - p p g p n a</m>
            <m cert="0.166666666666666667">v - - p p g p n v</m>
            <m cert="0.166666666666666667">v - - s p g p f v</m>
            <m cert="0.166666666666666667">v - - s p g p f n</m>
            <m cert="0.166666666666666667">v - - p p g p n n</m>
         </lm>
      </ana>
      <ana>
         <tok val="supersedendum"/>
         <lm>
            <l>supersedeo</l>
            <m cert="0.142857142857142857">v - - s p g p n a</m>
            <m cert="0.142857142857142857">v - - p p g p m g</m>
            <m cert="0.142857142857142857">v - - p p g p n g</m>
            <m cert="0.142857142857142857">v - - s p d a n a</m>
            <m cert="0.142857142857142857">v - - s p g p m a</m>
            <m cert="0.142857142857142857">v - - s p g p n v</m>
            <m cert="0.142857142857142857">v - - s p g p n n</m>
         </lm>
      </ana>
      <ana>
         <tok val="supersedens"/>
         <lm>
            <l>supersedeo</l>
            <m cert="0.142857142857142857">v - - s p p a f v</m>
            <m cert="0.142857142857142857">v - - s p p a m n</m>
            <m cert="0.142857142857142857">v - - s p p a m v</m>
            <m cert="0.142857142857142857">v - - s p p a f n</m>
            <m cert="0.142857142857142857">v - - s p p a n a</m>
            <m cert="0.142857142857142857">v - - s p p a n v</m>
            <m cert="0.142857142857142857">v - - s p p a n n</m>
         </lm>
      </ana>
      <ana>
         <tok val="supersedent"/>
         <lm>
            <l>supersedeo</l>
            <m>v - 3 p p i a</m>
         </lm>
      </ana>
      <ana>
         <tok val="supersedentibus"/>
         <lm>
            <l>supersedeo</l>
            <m cert="0.166666666666666667">v - - p p p a n d</m>
            <m cert="0.166666666666666667">v - - p p p a m d</m>
            <m cert="0.166666666666666667">v - - p p p a n b</m>
            <m cert="0.166666666666666667">v - - p p p a m b</m>
            <m cert="0.166666666666666667">v - - p p p a f b</m>
            <m cert="0.166666666666666667">v - - p p p a f d</m>
         </lm>
      </ana>
      <ana>
         <tok val="supersedere"/>
         <tok val="supersidere"/>
         <lm>
            <l>supersedeo</l>
            <m cert="0.333333333333333333">v - - - p n a</m>
            <m cert="0.333333333333333333">v - 2 s p m p</m>
            <m cert="0.333333333333333333">v - 2 s p i p</m>
         </lm>
      </ana>
      <ana>
         <tok val="supersederet"/>
         <lm>
            <l>supersedeo</l>
            <m>v - 3 s i s a</m>
         </lm>
      </ana>
      <ana>
         <tok val="supersederi"/>
         <lm>
            <l>supersedeo</l>
            <m>v - - - p n p</m>
         </lm>
      </ana>
      <ana>
         <tok val="supersederim"/>
         <lm>
            <l>supersedeo</l>
            <m>v - 1 s r s a</m>
         </lm>
      </ana>
      <ana>
         <tok val="supersederit"/>
         <lm>
            <l>supersedeo</l>
            <m cert="0.5">v - 3 s r s a</m>
            <m cert="0.5">v - 3 s t i a</m>
         </lm>
      </ana>
      <ana>
         <tok val="supersederunt"/>
         <lm>
            <l>supersedeo</l>
            <m>v - 3 p r i a</m>
         </lm>
      </ana>
      <ana>
         <tok val="supersedete"/>
         <lm>
            <l>supersedeo</l>
            <m>v - 2 p p m a</m>
         </lm>
      </ana>
      <ana>
         <tok val="supersedimus"/>
         <lm>
            <l>supersedeo</l>
            <m>v - 1 p r i a</m>
         </lm>
      </ana>
      <ana>
         <tok val="supersedissem"/>
         <lm>
            <l>supersedeo</l>
            <m>v - 1 s l s a</m>
         </lm>
      </ana>
      <ana>
         <tok val="supersedisset"/>
         <lm>
            <l>supersedeo</l>
            <m>v - 3 s l s a</m>
         </lm>
      </ana>
      <ana>
         <tok val="supersedit"/>
         <lm>
            <l>supersedeo</l>
            <m>v - 3 s r i a</m>
         </lm>
      </ana>
      <ana>
         <tok val="supersellium"/>
         <lm>
            <l>supersellium</l>
            <m cert="0.25">n - - s - - - n a</m>
            <m cert="0.25">n - - s - - - n v</m>
            <m cert="0.25">n - - s - - - n n</m>
            <m cert="0.25">n - - p - - - n g</m>
         </lm>
      </ana>
      <ana>
         <tok val="superseminator"/>
         <lm>
            <l>superseminator</l>
            <m cert="0.5">n - - s - - - m n</m>
            <m cert="0.5">n - - s - - - m v</m>
         </lm>
      </ana>
      <ana>
         <tok val="superseminauit"/>
         <tok val="superseminavit"/>
         <lm>
            <l>supersemino</l>
            <m>v - 3 s r i a</m>
         </lm>
      </ana>
      <ana>
         <tok val="supersessis"/>
         <lm>
            <l>supersedeo</l>
            <m cert="0.166666666666666667">v - - p r p p f d</m>
            <m cert="0.166666666666666667">v - - p r p p n d</m>
            <m cert="0.166666666666666667">v - - p r p p m d</m>
            <m cert="0.166666666666666667">v - - p r p p n b</m>
            <m cert="0.166666666666666667">v - - p r p p m b</m>
            <m cert="0.166666666666666667">v - - p r p p f b</m>
         </lm>
      </ana>
      <ana>
         <tok val="supersessum"/>
         <lm>
            <l>supersedeo</l>
            <m cert="0.142857142857142857">a - - s - - - n n</m>
            <m cert="0.142857142857142857">v - - p r p p m g</m>
            <m cert="0.142857142857142857">v - - s r p p n n</m>
            <m cert="0.142857142857142857">v - - p r p p n g</m>
            <m cert="0.142857142857142857">v - - s r p p n a</m>
            <m cert="0.142857142857142857">v - - s r p p n v</m>
            <m cert="0.142857142857142857">v - - s r p p m a</m>
         </lm>
      </ana>
      <ana>
         <tok val="supersessus"/>
         <lm>
            <l>supersedeo</l>
            <m>v - - s r p p m n</m>
         </lm>
      </ana>
      <ana>
         <tok val="supersidens"/>
         <lm>
            <l>supersido</l>
            <m cert="0.142857142857142857">v - - s p p a f v</m>
            <m cert="0.142857142857142857">v - - s p p a m n</m>
            <m cert="0.142857142857142857">v - - s p p a m v</m>
            <m cert="0.142857142857142857">v - - s p p a f n</m>
            <m cert="0.142857142857142857">v - - s p p a n a</m>
            <m cert="0.142857142857142857">v - - s p p a n v</m>
            <m cert="0.142857142857142857">v - - s p p a n n</m>
         </lm>
      </ana>
      <ana>
         <tok val="supersidet"/>
         <lm>
            <l>supersido</l>
            <m>v - 3 s f i a</m>
         </lm>
      </ana>
      <ana>
         <tok val="supersignabitur"/>
         <lm>
            <l>supersigno</l>
            <m>v - 3 s f i p</m>
         </lm>
      </ana>
      <ana>
         <tok val="supersignata"/>
         <lm>
            <l>supersigno</l>
            <m cert="0.166666666666666667">v - - p r p p n a</m>
            <m cert="0.166666666666666667">v - - s r p p f b</m>
            <m cert="0.166666666666666667">v - - s r p p f n</m>
            <m cert="0.166666666666666667">v - - s r p p f v</m>
            <m cert="0.166666666666666667">v - - p r p p n v</m>
            <m cert="0.166666666666666667">v - - p r p p n n</m>
         </lm>
      </ana>
      <ana>
         <tok val="supersilui"/>
         <lm>
            <l>supersileo</l>
            <m>v - 1 s r i a</m>
         </lm>
      </ana>
      <ana>
         <tok val="supersim"/>
         <lm>
            <l>supersum</l>
            <m>v - 1 s p s a</m>
         </lm>
      </ana>
      <ana>
         <tok val="supersistere"/>
         <lm>
            <l>supersisto</l>
            <m cert="0.25">v - - - p n a</m>
            <m cert="0.25">v - 2 s p m p</m>
            <m cert="0.25">v - 2 s p i p</m>
            <m cert="0.25">v - 2 s f i p</m>
         </lm>
      </ana>
      <ana>
         <tok val="supersistit"/>
         <lm>
            <l>supersisto</l>
            <m>v - 3 s p i a</m>
         </lm>
      </ana>
      <ana>
         <tok val="Supersit"/>
         <tok val="supersit"/>
         <tok val="supersitque"/>
         <lm>
            <l>supersum</l>
            <m>v - 3 s p s a</m>
         </lm>
      </ana>
      <ana>
         <tok val="superspargatur"/>
         <lm>
            <l>superspargo</l>
            <m>v - 3 s p s p</m>
         </lm>
      </ana>
      <ana>
         <tok val="superspargendae"/>
         <lm>
            <l>superspargo</l>
            <m cert="0.25">v - - p p g p f n</m>
            <m cert="0.25">v - - s p g p f g</m>
            <m cert="0.25">v - - s p g p f d</m>
            <m cert="0.25">v - - p p g p f v</m>
         </lm>
      </ana>
      <ana>
         <tok val="superspargentes"/>
         <lm>
            <l>superspargo</l>
            <m cert="0.166666666666666667">v - - p p p a m n</m>
            <m cert="0.166666666666666667">v - - p p p a f n</m>
            <m cert="0.166666666666666667">v - - p p p a m a</m>
            <m cert="0.166666666666666667">v - - p p p a m v</m>
            <m cert="0.166666666666666667">v - - p p p a f a</m>
            <m cert="0.166666666666666667">v - - p p p a f v</m>
         </lm>
      </ana>
      <ana>
         <tok val="supersparges"/>
         <lm>
            <l>superspargo</l>
            <m>v - 2 s f i a</m>
         </lm>
      </ana>
      <ana>
         <tok val="superspargis"/>
         <lm>
            <l>superspargo</l>
            <m>v - 2 s p i a</m>
         </lm>
      </ana>
      <ana>
         <tok val="superspargunt"/>
         <lm>
            <l>superspargo</l>
            <m>v - 3 p p i a</m>
         </lm>
      </ana>
      <ana>
         <tok val="supersparserunt"/>
         <lm>
            <l>superspargo</l>
            <m>v - 3 p r i a</m>
         </lm>
      </ana>
      <ana>
         <tok val="supersparso"/>
         <lm>
            <l>superspargo</l>
            <m cert="0.25">v - - s r p p n d</m>
            <m cert="0.25">v - - s r p p m d</m>
            <m cert="0.25">v - - s r p p m b</m>
            <m cert="0.25">v - - s r p p n b</m>
         </lm>
      </ana>
      <ana>
         <tok val="supersparsum"/>
         <lm>
            <l>superspargo</l>
            <m cert="0.142857142857142857">a - - s - - - n n</m>
            <m cert="0.142857142857142857">v - - p r p p m g</m>
            <m cert="0.142857142857142857">v - - s r p p n n</m>
            <m cert="0.142857142857142857">v - - p r p p n g</m>
            <m cert="0.142857142857142857">v - - s r p p n a</m>
            <m cert="0.142857142857142857">v - - s r p p n v</m>
            <m cert="0.142857142857142857">v - - s r p p m a</m>
         </lm>
      </ana>
      <ana>
         <tok val="supersperavi"/>
         <lm>
            <l>superspero</l>
            <m>v - 1 s r i a</m>
         </lm>
      </ana>
      <ana>
         <tok val="superspersi"/>
         <lm>
            <l>superspersus</l>
            <m cert="0.25">a - - s - - - m g</m>
            <m cert="0.25">a - - p - - - m v</m>
            <m cert="0.25">a - - p - - - m n</m>
            <m cert="0.25">a - - s - - - n g</m>
         </lm>
      </ana>
      <ana>
         <tok val="supersta"/>
         <lm>
            <l>supersto</l>
            <m>v - 2 s p m a</m>
         </lm>
      </ana>
      <ana>
         <tok val="superstabant"/>
         <lm>
            <l>supersto</l>
            <m>v - 3 p i i a</m>
         </lm>
      </ana>
      <ana>
         <tok val="superstabunt"/>
         <lm>
            <l>supersto</l>
            <m>v - 3 p f i a</m>
         </lm>
      </ana>
      <ana>
         <tok val="superstagnare"/>
         <lm>
            <l>superstagno</l>
            <m cert="0.333333333333333333">v - - - p n a</m>
            <m cert="0.333333333333333333">v - 2 s p m p</m>
            <m cert="0.333333333333333333">v - 2 s p i p</m>
         </lm>
      </ana>
      <ana>
         <tok val="superstagnas"/>
         <lm>
            <l>superstagno</l>
            <m>v - 2 s p i a</m>
         </lm>
      </ana>
      <ana>
         <tok val="superstagnavisset"/>
         <lm>
            <l>superstagno</l>
            <m>v - 3 s l s a</m>
         </lm>
      </ana>
      <ana>
         <tok val="superstans"/>
         <lm>
            <l>supersto</l>
            <m cert="0.142857142857142857">v - - s p p a f v</m>
            <m cert="0.142857142857142857">v - - s p p a m n</m>
            <m cert="0.142857142857142857">v - - s p p a m v</m>
            <m cert="0.142857142857142857">v - - s p p a f n</m>
            <m cert="0.142857142857142857">v - - s p p a n a</m>
            <m cert="0.142857142857142857">v - - s p p a n v</m>
            <m cert="0.142857142857142857">v - - s p p a n n</m>
         </lm>
      </ana>
      <ana>
         <tok val="superstant"/>
         <lm>
            <l>supersto</l>
            <m>v - 3 p p i a</m>
         </lm>
      </ana>
      <ana>
         <tok val="superstante"/>
         <tok val="superstanti"/>
         <lm>
            <l>supersto</l>
            <m cert="0.333333333333333333">v - - s p p a n b</m>
            <m cert="0.333333333333333333">v - - s p p a m b</m>
            <m cert="0.333333333333333333">v - - s p p a f b</m>
         </lm>
      </ana>
      <ana>
         <tok val="superstantem"/>
         <lm>
            <l>supersto</l>
            <m cert="0.5">v - - s p p a f a</m>
            <m cert="0.5">v - - s p p a m a</m>
         </lm>
      </ana>
      <ana>
         <tok val="superstantes"/>
         <lm>
            <l>supersto</l>
            <m cert="0.25">v - - p p p a m n</m>
            <m cert="0.25">v - - p p p a f n</m>
            <m cert="0.25">v - - p p p a m v</m>
            <m cert="0.25">v - - p p p a f v</m>
         </lm>
      </ana>
      <ana>
         <tok val="superstantes"/>
         <tok val="superstantis"/>
         <lm>
            <l>supersto</l>
            <m cert="0.5">v - - p p p a m a</m>
            <m cert="0.5">v - - p p p a f a</m>
         </lm>
      </ana>
      <ana>
         <tok val="superstantibus"/>
         <lm>
            <l>supersto</l>
            <m cert="0.166666666666666667">v - - p p p a n d</m>
            <m cert="0.166666666666666667">v - - p p p a m d</m>
            <m cert="0.166666666666666667">v - - p p p a n b</m>
            <m cert="0.166666666666666667">v - - p p p a m b</m>
            <m cert="0.166666666666666667">v - - p p p a f b</m>
            <m cert="0.166666666666666667">v - - p p p a f d</m>
         </lm>
      </ana>
      <ana>
         <tok val="superstantis"/>
         <lm>
            <l>supersto</l>
            <m cert="0.333333333333333333">v - - s p p a n g</m>
            <m cert="0.333333333333333333">v - - s p p a f g</m>
            <m cert="0.333333333333333333">v - - s p p a m g</m>
         </lm>
      </ana>
      <ana>
         <tok val="superstantium"/>
         <lm>
            <l>supersto</l>
            <m cert="0.333333333333333333">v - - p p p a m g</m>
            <m cert="0.333333333333333333">v - - p p p a f g</m>
            <m cert="0.333333333333333333">v - - p p p a n g</m>
         </lm>
      </ana>
      <ana>
         <tok val="superstare"/>
         <lm>
            <l>supersto</l>
            <m cert="0.333333333333333333">v - - - p n a</m>
            <m cert="0.333333333333333333">v - 2 s p m p</m>
            <m cert="0.333333333333333333">v - 2 s p i p</m>
         </lm>
      </ana>
      <ana>
         <tok val="superstarent"/>
         <lm>
            <l>supersto</l>
            <m>v - 3 p i s a</m>
         </lm>
      </ana>
      <ana>
         <tok val="superstaret"/>
         <lm>
            <l>supersto</l>
            <m>v - 3 s i s a</m>
         </lm>
      </ana>
      <ana>
         <tok val="superstas"/>
         <lm>
            <l>supersto</l>
            <m>v - 2 s p i a</m>
         </lm>
      </ana>
      <ana>
         <tok val="superstat"/>
         <lm>
            <l>supersto</l>
            <m>v - 3 s p i a</m>
         </lm>
      </ana>
      <ana>
         <tok val="superstatis"/>
         <tok val="superstitis"/>
         <lm>
            <l>supersto</l>
            <m cert="0.166666666666666667">v - - p r p p f d</m>
            <m cert="0.166666666666666667">v - - p r p p n d</m>
            <m cert="0.166666666666666667">v - - p r p p m d</m>
            <m cert="0.166666666666666667">v - - p r p p n b</m>
            <m cert="0.166666666666666667">v - - p r p p m b</m>
            <m cert="0.166666666666666667">v - - p r p p f b</m>
         </lm>
      </ana>
      <ana>
         <tok val="superstatis"/>
         <lm>
            <l>supersto</l>
            <m>v - 2 p p i a</m>
         </lm>
      </ana>
      <ana>
         <tok val="supersternere"/>
         <lm>
            <l>supersterno</l>
            <m cert="0.25">v - - - p n a</m>
            <m cert="0.25">v - 2 s p m p</m>
            <m cert="0.25">v - 2 s p i p</m>
            <m cert="0.25">v - 2 s f i p</m>
         </lm>
      </ana>
      <ana>
         <tok val="supersternis"/>
         <lm>
            <l>supersterno</l>
            <m>v - 2 s p i a</m>
         </lm>
      </ana>
      <ana>
         <tok val="supersternuntur"/>
         <lm>
            <l>supersterno</l>
            <m>v - 3 p p i p</m>
         </lm>
      </ana>
      <ana>
         <tok val="superstet"/>
         <lm>
            <l>supersto</l>
            <m>v - 3 s p s a</m>
         </lm>
      </ana>
      <ana>
         <tok val="supersteterant"/>
         <lm>
            <l>supersto</l>
            <m>v - 3 p l i a</m>
         </lm>
      </ana>
      <ana>
         <tok val="superstillabis"/>
         <lm>
            <l>superstillo</l>
            <m>v - 2 s f i a</m>
         </lm>
      </ana>
      <ana>
         <tok val="superstitentque"/>
         <lm>
            <l>superstito</l>
            <m>v - 3 p p s a</m>
         </lm>
      </ana>
      <ana>
         <tok val="superstitet"/>
         <lm>
            <l>superstito</l>
            <m>v - 3 s p s a</m>
         </lm>
      </ana>
      <ana>
         <tok val="superstiti"/>
         <lm cert="0.5">
            <l>supersto</l>
            <m cert="0.25">v - - p r p p m v</m>
            <m cert="0.25">v - - p r p p m n</m>
            <m cert="0.25">v - - s r p p m g</m>
            <m cert="0.25">v - - s r p p n g</m>
         </lm>
         <lm cert="0.5">
            <l>supersisto</l>
            <m>v - 1 s r i a</m>
         </lm>
      </ana>
      <ana>
         <tok val="Superstitionem"/>
         <tok val="superstitionem"/>
         <lm>
            <l>superstitio</l>
            <m>n - - s - - - f a</m>
         </lm>
      </ana>
      <ana>
         <tok val="superstitioni"/>
         <lm>
            <l>superstitio</l>
            <m>n - - s - - - f d</m>
         </lm>
      </ana>
      <ana>
         <tok val="superstitionibus"/>
         <lm>
            <l>superstitio</l>
            <m cert="0.5">n - - p - - - f d</m>
            <m cert="0.5">n - - p - - - f b</m>
         </lm>
      </ana>
      <ana>
         <tok val="superstitionis"/>
         <lm>
            <l>superstitio</l>
            <m>n - - s - - - f g</m>
         </lm>
      </ana>
      <ana>
         <tok val="superstitionum"/>
         <lm>
            <l>superstitio</l>
            <m>n - - p - - - f g</m>
         </lm>
      </ana>
      <ana>
         <tok val="superstitiosae"/>
         <lm>
            <l>superstitiosus</l>
            <m cert="0.25">a - - p - - - f v</m>
            <m cert="0.25">a - - s - - - f d</m>
            <m cert="0.25">a - - p - - - f n</m>
            <m cert="0.25">a - - s - - - f g</m>
         </lm>
      </ana>
      <ana>
         <tok val="superstitiosam"/>
         <lm>
            <l>superstitiosus</l>
            <m>a - - s - - - f a</m>
         </lm>
      </ana>
      <ana>
         <tok val="superstitiosi"/>
         <lm>
            <l>superstitiosus</l>
            <m cert="0.25">a - - s - - - m g</m>
            <m cert="0.25">a - - p - - - m v</m>
            <m cert="0.25">a - - p - - - m n</m>
            <m cert="0.25">a - - s - - - n g</m>
         </lm>
      </ana>
      <ana>
         <tok val="superstitiosiores"/>
         <lm>
            <l>superstitiosus</l>
            <m cert="0.166666666666666667">a - - p - - - m v c</m>
            <m cert="0.166666666666666667">a - - p - - - m n c</m>
            <m cert="0.166666666666666667">a - - p - - - m a c</m>
            <m cert="0.166666666666666667">a - - p - - - f a c</m>
            <m cert="0.166666666666666667">a - - p - - - f v c</m>
            <m cert="0.166666666666666667">a - - p - - - f n c</m>
         </lm>
      </ana>
      <ana>
         <tok val="superstitiosis"/>
         <lm>
            <l>superstitiosus</l>
            <m cert="0.166666666666666667">a - - p - - - n d</m>
            <m cert="0.166666666666666667">a - - p - - - f b</m>
            <m cert="0.166666666666666667">a - - p - - - f d</m>
            <m cert="0.166666666666666667">a - - p - - - m d</m>
            <m cert="0.166666666666666667">a - - p - - - m b</m>
            <m cert="0.166666666666666667">a - - p - - - n b</m>
         </lm>
      </ana>
      <ana>
         <tok val="superstitioso"/>
         <lm>
            <l>superstitiosus</l>
            <m cert="0.25">a - - s - - - n b</m>
            <m cert="0.25">a - - s - - - m d</m>
            <m cert="0.25">a - - s - - - n d</m>
            <m cert="0.25">a - - s - - - m b</m>
         </lm>
      </ana>
      <ana>
         <tok val="superstitiosos"/>
         <lm>
            <l>superstitiosus</l>
            <m>a - - p - - - m a</m>
         </lm>
      </ana>
      <ana>
         <tok val="superstituerem"/>
         <lm>
            <l>superstatuo</l>
            <m>v - 1 s i s a</m>
         </lm>
      </ana>
      <ana>
         <tok val="superstitum"/>
         <lm>
            <l>supersto</l>
            <m cert="0.166666666666666667">a - - s - - - n n</m>
            <m cert="0.166666666666666667">v - - s r p p m a</m>
            <m cert="0.166666666666666667">v - - s r p p n a</m>
            <m cert="0.166666666666666667">v - - p r p p m g</m>
            <m cert="0.166666666666666667">v - - s r p p n n</m>
            <m cert="0.166666666666666667">v - - p r p p n g</m>
         </lm>
      </ana>
      <ana>
         <tok val="superstrati"/>
         <lm>
            <l>supersterno</l>
            <m cert="0.25">v - - s r p p n g</m>
            <m cert="0.25">v - - p r p p m v</m>
            <m cert="0.25">v - - s r p p m g</m>
            <m cert="0.25">v - - p r p p m n</m>
         </lm>
      </ana>
      <ana>
         <tok val="superstratis"/>
         <lm>
            <l>supersterno</l>
            <m cert="0.166666666666666667">v - - p r p p f d</m>
            <m cert="0.166666666666666667">v - - p r p p n d</m>
            <m cert="0.166666666666666667">v - - p r p p m d</m>
            <m cert="0.166666666666666667">v - - p r p p n b</m>
            <m cert="0.166666666666666667">v - - p r p p m b</m>
            <m cert="0.166666666666666667">v - - p r p p f b</m>
         </lm>
      </ana>
      <ana>
         <tok val="superstratum"/>
         <lm>
            <l>supersterno</l>
            <m cert="0.142857142857142857">a - - s - - - n n</m>
            <m cert="0.142857142857142857">v - - p r p p m g</m>
            <m cert="0.142857142857142857">v - - s r p p n n</m>
            <m cert="0.142857142857142857">v - - p r p p n g</m>
            <m cert="0.142857142857142857">v - - s r p p n a</m>
            <m cert="0.142857142857142857">v - - s r p p n v</m>
            <m cert="0.142857142857142857">v - - s r p p m a</m>
         </lm>
      </ana>
      <ana>
         <tok val="superstratus"/>
         <lm>
            <l>supersterno</l>
            <m>v - - s r p p m n</m>
         </lm>
      </ana>
      <ana>
         <tok val="superstrictis"/>
         <lm>
            <l>superstringo</l>
            <m cert="0.166666666666666667">v - - p r p p f d</m>
            <m cert="0.166666666666666667">v - - p r p p n d</m>
            <m cert="0.166666666666666667">v - - p r p p m d</m>
            <m cert="0.166666666666666667">v - - p r p p n b</m>
            <m cert="0.166666666666666667">v - - p r p p m b</m>
            <m cert="0.166666666666666667">v - - p r p p f b</m>
         </lm>
      </ana>
      <ana>
         <tok val="superstrictus"/>
         <lm>
            <l>superstringo</l>
            <m>v - - s r p p m n</m>
         </lm>
      </ana>
      <ana>
         <tok val="superstruatur"/>
         <lm>
            <l>superstruo</l>
            <m>v - 3 s p s p</m>
         </lm>
      </ana>
      <ana>
         <tok val="superstructis"/>
         <lm>
            <l>superstruo</l>
            <m cert="0.166666666666666667">v - - p r p p f d</m>
            <m cert="0.166666666666666667">v - - p r p p n d</m>
            <m cert="0.166666666666666667">v - - p r p p m d</m>
            <m cert="0.166666666666666667">v - - p r p p n b</m>
            <m cert="0.166666666666666667">v - - p r p p m b</m>
            <m cert="0.166666666666666667">v - - p r p p f b</m>
         </lm>
      </ana>
      <ana>
         <tok val="superstructus"/>
         <lm>
            <l>superstruo</l>
            <m>v - - s r p p m n</m>
         </lm>
      </ana>
      <ana>
         <tok val="superstruere"/>
         <lm>
            <l>superstruo</l>
            <m cert="0.25">v - - - p n a</m>
            <m cert="0.25">v - 2 s p m p</m>
            <m cert="0.25">v - 2 s p i p</m>
            <m cert="0.25">v - 2 s f i p</m>
         </lm>
      </ana>
      <ana>
         <tok val="superstrui"/>
         <lm>
            <l>superstruo</l>
            <m>v - - - p n p</m>
         </lm>
      </ana>
      <ana>
         <tok val="superstruit"/>
         <lm>
            <l>superstruo</l>
            <m>v - 3 s p i a</m>
         </lm>
      </ana>
      <ana>
         <tok val="superstruunt"/>
         <lm>
            <l>superstruo</l>
            <m>v - 3 p p i a</m>
         </lm>
      </ana>
      <ana>
         <tok val="superstruuntur"/>
         <lm>
            <l>superstruo</l>
            <m>v - 3 p p i p</m>
         </lm>
      </ana>
      <ana>
         <tok val="superstruxeras"/>
         <lm>
            <l>superstruo</l>
            <m>v - 2 s l i a</m>
         </lm>
      </ana>
      <ana>
         <tok val="superstruxeris"/>
         <lm>
            <l>superstruo</l>
            <m cert="0.5">v - 2 s t i a</m>
            <m cert="0.5">v - 2 s r s a</m>
         </lm>
      </ana>
      <ana>
         <tok val="superstruxit"/>
         <tok val="superstruxitque"/>
         <lm>
            <l>superstruo</l>
            <m>v - 3 s r i a</m>
         </lm>
      </ana>
      <ana>
         <tok val="supersubstantialem"/>
         <lm>
            <l>supersubstantialis</l>
            <m cert="0.5">a - - s - - - f a</m>
            <m cert="0.5">a - - s - - - m a</m>
         </lm>
      </ana>
      <ana>
         <tok val="supersubstantialis"/>
         <lm>
            <l>supersubstantialis</l>
            <m cert="0.111111111111111111">a - - s - - - f g</m>
            <m cert="0.111111111111111111">a - - p - - - m a</m>
            <m cert="0.111111111111111111">a - - s - - - m g</m>
            <m cert="0.111111111111111111">a - - s - - - f n</m>
            <m cert="0.111111111111111111">a - - s - - - f v</m>
            <m cert="0.111111111111111111">a - - p - - - f a</m>
            <m cert="0.111111111111111111">a - - s - - - m n</m>
            <m cert="0.111111111111111111">a - - s - - - m v</m>
            <m cert="0.111111111111111111">a - - s - - - n g</m>
         </lm>
      </ana>
      <ana>
         <tok val="supersubstantivus"/>
         <lm>
            <l>supersubstantivus</l>
            <m>a - - s - - - m n</m>
         </lm>
      </ana>
      <ana>
         <tok val="supersuerit"/>
         <lm>
            <l>supersuo</l>
            <m cert="0.5">v - 3 s r s a</m>
            <m cert="0.5">v - 3 s t i a</m>
         </lm>
      </ana>
      <ana>
         <tok val="supersuerunt"/>
         <lm>
            <l>supersuo</l>
            <m>v - 3 p r i a</m>
         </lm>
      </ana>
      <ana>
         <tok val="supersuit"/>
         <lm>
            <l>supersuo</l>
            <m cert="0.5">v - 3 s r i a</m>
            <m cert="0.5">v - 3 s p i a</m>
         </lm>
      </ana>
      <ana>
         <tok val="supersumus"/>
         <lm>
            <l>supersum</l>
            <m>v - 1 p p i a</m>
         </lm>
      </ana>
      <ana>
         <tok val="superscandentes"/>
         <lm>
            <l>superscando</l>
            <m cert="0.166666666666666667">v - - p p p a f a</m>
            <m cert="0.166666666666666667">v - - p p p a f n</m>
            <m cert="0.166666666666666667">v - - p p p a f v</m>
            <m cert="0.166666666666666667">v - - p p p a m a</m>
            <m cert="0.166666666666666667">v - - p p p a m n</m>
            <m cert="0.166666666666666667">v - - p p p a m v</m>
         </lm>
      </ana>
      <ana>
         <tok val="superscribitur"/>
         <lm>
            <l>superscribo</l>
            <m>v - 3 s p i p</m>
         </lm>
      </ana>
      <ana>
         <tok val="supersedebat"/>
         <lm>
            <l>supersedeo</l>
            <m>v - 3 s i i a</m>
         </lm>
      </ana>
      <ana>
         <tok val="supersederemus"/>
         <lm>
            <l>supersedeo</l>
            <m>v - 1 p i s a</m>
         </lm>
      </ana>
      <ana>
         <tok val="supersidentes"/>
         <lm>
            <l>supersedeo</l>
            <m cert="0.166666666666666667">v - - p p p a f a</m>
            <m cert="0.166666666666666667">v - - p p p a f n</m>
            <m cert="0.166666666666666667">v - - p p p a f v</m>
            <m cert="0.166666666666666667">v - - p p p a m a</m>
            <m cert="0.166666666666666667">v - - p p p a m n</m>
            <m cert="0.166666666666666667">v - - p p p a m v</m>
         </lm>
      </ana>
      <ana>
         <tok val="supersidere"/>
         <lm>
            <l>supersedeo</l>
            <m>v - 2 s f i p</m>
         </lm>
      </ana>
      <ana>
         <tok val="superstanti"/>
         <lm>
            <l>supersto</l>
            <m cert="0.333333333333333333">v - - s p p a f d</m>
            <m cert="0.333333333333333333">v - - s p p a m d</m>
            <m cert="0.333333333333333333">v - - s p p a n d</m>
         </lm>
      </ana>
      <ana>
         <tok val="superstate"/>
         <lm>
            <l>supersto</l>
            <m>v - 2 p p m a</m>
         </lm>
      </ana>
      <ana>
         <tok val="supersternant"/>
         <lm>
            <l>supersterno</l>
            <m>v - 3 p p s a</m>
         </lm>
      </ana>
      <ana>
         <tok val="superstravit"/>
         <lm>
            <l>supersterno</l>
            <m>v - 3 s r i a</m>
         </lm>
      </ana>
      <ana>
         <tok val="superstructa"/>
         <lm>
            <l>superstruo</l>
            <m cert="0.166666666666666667">v - - p r p p n a</m>
            <m cert="0.166666666666666667">v - - p r p p n n</m>
            <m cert="0.166666666666666667">v - - p r p p n v</m>
            <m cert="0.166666666666666667">v - - s r p p f b</m>
            <m cert="0.166666666666666667">v - - s r p p f n</m>
            <m cert="0.166666666666666667">v - - s r p p f v</m>
         </lm>
      </ana>
   </body>
</TAN-A-lm>
